Metadata-Version: 2.1
Name: NehorayRapid1
Version: 0.0.1
Summary: Rapid base tools package
Author: Nehoray melamed
Author-email: nehoraymelamed@galeoai.com
Keywords: nehoray melamed
Classifier: Development Status :: 1 - Planning
Classifier: Intended Audience :: Developers
Classifier: Programming Language :: Python :: 3
Classifier: Operating System :: Unix
Classifier: Operating System :: MacOS :: MacOS X
Classifier: Operating System :: Microsoft :: Windows
License-File: LICENSE
Requires-Dist: absl-py (==1.0.0)
Requires-Dist: albumentations (==1.1.0)
Requires-Dist: astropy (==5.0.4)
Requires-Dist: asttokens
Requires-Dist: astunparse (==1.6.3)
Requires-Dist: atomicwrites (==1.4.0)
Requires-Dist: attrs (==21.4.0)
Requires-Dist: backcall
Requires-Dist: bcrypt (==3.2.0)
Requires-Dist: brotlipy (==0.7.0)
Requires-Dist: cachetools (==5.0.0)
Requires-Dist: certifi
Requires-Dist: cffi
Requires-Dist: charset-normalizer (==2.0.12)
Requires-Dist: cli-exit-tools (==1.2.3)
Requires-Dist: click (==8.1.2)
Requires-Dist: colorama
Requires-Dist: colour-demosaicing
Requires-Dist: cryptography
Requires-Dist: csaps (==1.1.0)
Requires-Dist: cycler (==0.11.0)
Requires-Dist: Cython (==0.29.28)
Requires-Dist: decorator
Requires-Dist: dill (==0.3.4)
Requires-Dist: easydict (==1.9)
Requires-Dist: einops (==0.4.1)
Requires-Dist: executing
Requires-Dist: ffmpeg (==1.4)
Requires-Dist: ffmpeg-python (==0.2.0)
Requires-Dist: flatbuffers (==2.0)
Requires-Dist: fonttools (==4.32.0)
Requires-Dist: future (==0.18.2)
Requires-Dist: gast (==0.5.3)
Requires-Dist: google-auth (==2.6.4)
Requires-Dist: google-auth-oauthlib (==0.4.6)
Requires-Dist: google-pasta (==0.2.0)
Requires-Dist: grpcio (==1.44.0)
Requires-Dist: h5py (==3.6.0)
Requires-Dist: idna
Requires-Dist: image-registration (==0.2.5)
Requires-Dist: imageio (==2.16.2)
Requires-Dist: imageio-ffmpeg (==0.4.7)
Requires-Dist: importlib-metadata (==4.11.3)
Requires-Dist: imutils (==0.5.4)
Requires-Dist: iniconfig (==1.1.1)
Requires-Dist: ipython
Requires-Dist: jedi
Requires-Dist: joblib
Requires-Dist: keopscore (==2.1)
Requires-Dist: keras (==2.8.0)
Requires-Dist: Keras-Preprocessing (==1.1.2)
Requires-Dist: kiwisolver (==1.4.2)
Requires-Dist: klepto (==0.2.1)
Requires-Dist: kornia (==0.6.5)
Requires-Dist: kornia-moons (==0.2.0)
Requires-Dist: lib-detect-testenv (==2.0.2)
Requires-Dist: lib-programname (==2.0.4)
Requires-Dist: libclang (==13.0.0)
Requires-Dist: lmdb (==1.3.0)
Requires-Dist: Markdown (==3.3.6)
Requires-Dist: matplotlib (==3.5.1)
Requires-Dist: matplotlib-inline
Requires-Dist: mkl-fft (==1.3.1)
Requires-Dist: mkl-random
Requires-Dist: mkl-service (==2.4.0)
Requires-Dist: moviepy (==1.0.3)
Requires-Dist: natsort (==8.1.0)
Requires-Dist: networkx (==2.8)
Requires-Dist: numpngw (==0.1.0)
Requires-Dist: numpy
Requires-Dist: oauthlib (==3.2.0)
Requires-Dist: opencv-python (==4.5.5.64)
Requires-Dist: opencv-python-headless (==4.5.5.64)
Requires-Dist: opt-einsum (==3.3.0)
Requires-Dist: packaging (==21.3)
Requires-Dist: pandas (==1.4.3)
Requires-Dist: paramiko (==2.10.3)
Requires-Dist: parso
Requires-Dist: pickleshare
Requires-Dist: Pillow (==9.2.0)
Requires-Dist: pluggy (==1.0.0)
Requires-Dist: pox (==0.3.0)
Requires-Dist: proglog (==0.1.10)
Requires-Dist: prompt-toolkit
Requires-Dist: protobuf (==3.20.0)
Requires-Dist: pure-eval
Requires-Dist: py (==1.11.0)
Requires-Dist: pyasn1 (==0.4.8)
Requires-Dist: pyasn1-modules (==0.2.8)
Requires-Dist: pybind11 (==2.9.2)
Requires-Dist: pycparser
Requires-Dist: pyerfa (==2.0.0.1)
Requires-Dist: Pygments
Requires-Dist: pykeops (==2.1)
Requires-Dist: PyMsgBox (==1.0.9)
Requires-Dist: PyNaCl (==1.5.0)
Requires-Dist: pyOpenSSL
Requires-Dist: pyparsing (==3.0.8)
Requires-Dist: PySocks
Requires-Dist: pytest (==7.1.1)
Requires-Dist: python-dateutil (==2.8.2)
Requires-Dist: pytube (==12.1.0)
Requires-Dist: pytz (==2022.1)
Requires-Dist: PyWavelets (==1.3.0)
Requires-Dist: PyYAML (==6.0)
Requires-Dist: qudida (==0.0.4)
Requires-Dist: requests
Requires-Dist: requests-oauthlib (==1.3.1)
Requires-Dist: rsa (==4.8)
Requires-Dist: scikit-image (==0.19.2)
Requires-Dist: scikit-learn
Requires-Dist: scipy (==1.8.0)
Requires-Dist: scp (==0.14.4)
Requires-Dist: seaborn
Requires-Dist: six
Requires-Dist: shapely
Requires-Dist: stack-data
Requires-Dist: tensorboard (==2.8.0)
Requires-Dist: tensorboard-data-server (==0.6.1)
Requires-Dist: tensorboard-plugin-wit (==1.8.1)
Requires-Dist: tensorboardX (==2.5)
Requires-Dist: tensorflow (==2.8.0)
Requires-Dist: tensorflow-io-gcs-filesystem (==0.24.0)
Requires-Dist: termcolor (==1.1.0)
Requires-Dist: tf-estimator-nightly (==2.8.0.dev2021122109)
Requires-Dist: threadpoolctl (==3.1.0)
Requires-Dist: tifffile (==2022.4.8)
Requires-Dist: tomli (==2.0.1)
Requires-Dist: torch-interpol (==0.1.1)
Requires-Dist: tqdm (==4.64.0)
Requires-Dist: traitlets
Requires-Dist: typing-extensions
Requires-Dist: urllib3
Requires-Dist: wcwidth
Requires-Dist: Werkzeug (==2.1.1)
Requires-Dist: win-inet-pton
Requires-Dist: wincertstore (==0.2)
Requires-Dist: wrapt (==1.14.0)
Requires-Dist: zipp (==3.8.0)
